radinNFP/__init__.py
radinNFP/radinNFP.py
NFPRadin1-0.0.1.dist-info/METADATA
NFPRadin1-0.0.1.dist-info/WHEEL
NFPRadin1-0.0.1.dist-info/top_level.txt
NFPRadin1-0.0.1.dist-info/RECORD
