Metadata-Version: 2.1
Name: NFPRadin1
Version: 0.0.1
Summary: a package that will create NFP for two Polygons
Author: Radin Sign Factory
Requires-Python: >=3.9
Requires-Dist: matplotlib
Requires-Dist: numpy
